alpacloud/__init__.py
alpacloud/lens/__init__.py
alpacloud/lens/k8s.py
alpacloud/lens/models.py
alpacloud/lens/util/__init__.py
alpacloud/lens/util/sentinel.py
alpacloud/lens/util/type.py
alpacloud.lens-0.1.0.dist-info/METADATA
alpacloud.lens-0.1.0.dist-info/WHEEL
alpacloud.lens-0.1.0.dist-info/namespace_packages.txt
alpacloud.lens-0.1.0.dist-info/top_level.txt
alpacloud.lens-0.1.0.dist-info/RECORD
